.gitmodules
MANIFEST.in
Makefile.in
README.md
configure.ac
setup.py
config/circuits/bristlecone_48_1-16-1_0.txt
config/circuits/bristlecone_48_1-20-1_0.txt
config/circuits/bristlecone_48_1-24-1_0.txt
config/circuits/bristlecone_48_1-32-1_0.txt
config/circuits/bristlecone_48_1-40-1_0.txt
config/circuits/bristlecone_60_1-24-1_0.txt
config/circuits/bristlecone_60_1-32-1_0.txt
config/circuits/bristlecone_60_1-40-1_0.txt
config/circuits/bristlecone_70_1-12-1_0.txt
config/circuits/bristlecone_70_1-16-1_0.txt
config/circuits/bristlecone_70_1-20-1_0.txt
config/circuits/bristlecone_70_1-24-1_0.txt
config/circuits/bristlecone_70_1-32-1_0.txt
config/circuits/bristlecone_70_1-40-1_0.txt
config/circuits/rectangular_11x12_1-16-1_0.txt
config/circuits/rectangular_11x12_1-24-1_0.txt
config/circuits/rectangular_11x12_1-32-1_0.txt
config/circuits/rectangular_11x12_1-40-1_0.txt
config/circuits/rectangular_2x2_1-2-1_0.txt
config/circuits/rectangular_4x4_1-16-1_0.txt
config/circuits/rectangular_6x6_1-16-1_0.txt
config/circuits/rectangular_6x6_1-24-1_0.txt
config/circuits/rectangular_6x6_1-32-1_0.txt
config/circuits/rectangular_7x7_1-32-1_0.txt
config/circuits/rectangular_7x7_1-40-1_0.txt
config/circuits/rectangular_7x7_1-48-1_0.txt
config/circuits/rectangular_8x8_1-24-1_0.txt
config/circuits/rectangular_8x8_1-32-1_0.txt
config/circuits/rectangular_8x8_1-40-1_0.txt
config/circuits/rectangular_8x9_1-24-1_0.txt
config/circuits/rectangular_8x9_1-32-1_0.txt
config/circuits/rectangular_8x9_1-40-1_0.txt
config/circuits/rochester_53_10_0_pABC.txt
config/circuits/rochester_53_12_0_pABC.txt
config/circuits/rochester_53_16_0_pABC.txt
config/circuits/rochester_53_20_0_pABC.txt
config/circuits/rochester_53_4_0_pABC.txt
config/circuits/rochester_53_8_0_pABC.txt
config/circuits/sycamore_53_10_0.txt
config/circuits/sycamore_53_4_0.txt
config/circuits/sycamore_53_5_0.txt
config/circuits/sycamore_53_6_0.txt
config/circuits/sycamore_53_8_0.txt
config/circuits/test.txt
config/grid/bristlecone_48.txt
qflexcirq.egg-info/PKG-INFO
qflexcirq.egg-info/SOURCES.txt
qflexcirq.egg-info/dependency_links.txt
qflexcirq.egg-info/requires.txt
qflexcirq.egg-info/top_level.txt
