Metadata-Version: 2.1
Name: qflexcirq
Version: 0.0.5
Summary: A Google Cirq interface for QFlex
Home-page: https://github.com/ngnrsaa/qflex
Author: The QFlex Contributors
License: Apache 2
Platform: UNKNOWN
Requires-Python: >=3.6
